pp_recordio/__init__.py
pp_recordio/pp_recordio.py
pp_recordio/pp_recordio_lib.so
pp_recordio/pp_recordio_lib_darwin_amd64.so
pp_recordio/pp_recordio_lib_darwin_arm64.so
pp_recordio/pp_recordio_lib_linux_amd64.so
pp_recordio/pp_recordio_lib_linux_arm64.so
pp_recordio/pp_recordio_test.py
pp_recordio-0.1.6.dist-info/METADATA
pp_recordio-0.1.6.dist-info/WHEEL
pp_recordio-0.1.6.dist-info/top_level.txt
pp_recordio-0.1.6.dist-info/RECORD
