Metadata-Version: 2.1
Name: pp_recordio
Version: 0.1.6
Summary: Post Perception's RecordIO facsimile.
Home-page: https://github.com/postperception/pp_recordio
Author: Sam Liu
Author-email: sam@postperception.com
License: MIT
Classifier: Development Status :: 3 - Alpha
Classifier: Intended Audience :: Developers
Classifier: License :: OSI Approved :: MIT License
Classifier: Programming Language :: Python :: 3
Classifier: Programming Language :: Python :: 3.6
Classifier: Programming Language :: Python :: 3.7
Classifier: Programming Language :: Python :: 3.8
Classifier: Programming Language :: Python :: 3.9
Requires-Python: >=3.6
